[
  {
    "masuda_id": "20200314085849",
    "title": "anond:20200313202224",
    "content": "「名詞では形容詞（あるいは名詞として振舞わない名詞を刷り込まれている）名詞」と「求められない（あるいはそう思い込んでいる）名詞」は名詞もその持てる名詞から名詞に得られる名詞を得ていないので、「名詞だから～でしょ」「名詞だから～でしょ」という名詞に名詞する。",
    "bookmark_count": 0,
    "category": null
  },
  {
    "masuda_id": "20200314085845",
    "title": "anond:20200314085754",
    "content": "名詞も名詞名詞と名詞名詞を作って同じ名詞をすれば形容詞名詞に名詞に食わない名詞も殴れるぞ",
    "bookmark_count": 0,
    "category": null
  },
  {
    "masuda_id": "20200314085815",
    "title": "anond:20200314021948",
    "content": "名詞は名詞名詞から名詞されている名詞は名詞名詞では名詞(名詞",
    "bookmark_count": 0,
    "category": null
  },
  {
    "masuda_id": "20200314085754",
    "title": "俺も恋人がいる立場から非モテ増田にブコメ説教したかった ",
    "content": "特に名詞の名詞名詞名詞に「よくわからないけど名詞からの名詞だけが名詞なの？」とか「名詞は名詞の名詞を満たす名詞に名詞してる名詞では名詞」名詞なよくある名詞してみたかった名詞とか名詞がいる名詞で名詞名詞にこういう名詞言う名詞名詞名詞形容詞と思う名詞だよな",
    "bookmark_count": 0,
    "category": null
  },
  {
    "masuda_id": "20200314085745",
    "title": "はてブで叩かれても気にすることはない ",
    "content": "名詞名詞読まずにこういう名詞すれば名詞もらえるだろうなって名詞書いたら実際に名詞に名詞もらえるから。その名詞の名詞しかいない名詞から。",
    "bookmark_count": 0,
    "category": null
  },
  {
    "masuda_id": "20200314085732",
    "title": "anond:20200314085653",
    "content": "名詞名詞名詞名詞名詞",
    "bookmark_count": 0,
    "category": null
  },
  {
    "masuda_id": "20200314085653",
    "title": "",
    "content": "名詞名詞するな。にゃーんもやめろ。粛々と名詞やられててくれ。",
    "bookmark_count": 0,
    "category": null
  },
  {
    "masuda_id": "20200314085630",
    "title": "Uber Eater ",
    "content": "名詞の名詞か！",
    "bookmark_count": 0,
    "category": null
  },
  {
    "masuda_id": "20200314085611",
    "title": "anond:20200314085429",
    "content": "名詞名詞と名詞名詞は同じ名詞形容詞よ",
    "bookmark_count": 0,
    "category": null
  },
  {
    "masuda_id": "20200314085544",
    "title": "anond:20200314085459",
    "content": "つ名詞",
    "bookmark_count": 0,
    "category": null
  },
  {
    "masuda_id": "20200314085503",
    "title": "anond:20200313202224",
    "content": "名詞ならまだしも名詞とか名詞とかを名詞に出す名詞な名詞になってからの名詞なら「名詞にどうされた」名詞「名詞が名詞をしたか」で測れよ。名詞名詞名詞の名詞だわ。",
    "bookmark_count": 0,
    "category": null
  },
  {
    "masuda_id": "20200314085459",
    "title": "マックとフレッシュネスとモスとロッテリアのハンバーガ全部食べたいねん ",
    "content": "名詞行く名詞名詞やねん。名詞食べられる名詞名詞や。名詞でも形容詞わ。",
    "bookmark_count": 0,
    "category": null
  },
  {
    "masuda_id": "20200314085452",
    "title": "新しい朝ガキ ",
    "content": "名詞の名詞",
    "bookmark_count": 0,
    "category": null
  },
  {
    "masuda_id": "20200314085429",
    "title": "anond:20200314084248",
    "content": "いや。名詞名詞に名詞だよ。",
    "bookmark_count": 0,
    "category": null
  },
  {
    "masuda_id": "20200314085413",
    "title": "財政出動しても海外にお金逃げるだけじゃないの ",
    "content": "名詞は名詞ばっかだし、名詞も名詞名詞じゃないし。",
    "bookmark_count": 0,
    "category": null
  },
  {
    "masuda_id": "20200314085317",
    "title": "下書き自動保存 ",
    "content": "う名詞",
    "bookmark_count": 0,
    "category": null
  },
  {
    "masuda_id": "20200314085015",
    "title": "麻原ゲートウェイ",
    "content": "名詞への名詞が開かれた",
    "bookmark_count": 0,
    "category": null
  },
  {
    "masuda_id": "20200314084918",
    "title": "anond:20200314083121",
    "content": "名詞の名詞を名詞名詞する名詞でしょ？知ってる。",
    "bookmark_count": 0,
    "category": null
  },
  {
    "masuda_id": "20200314084834",
    "title": "anond:20200314084505",
    "content": "名詞で食べさせられた名詞がゴマンとい名詞で形容詞",
    "bookmark_count": 0,
    "category": null
  },
  {
    "masuda_id": "20200314084753",
    "title": "anond:20200314082943",
    "content": "名詞名詞が名詞にならないと撃ってくれない名詞じゃん名詞じゃん",
    "bookmark_count": 0,
    "category": null
  },
  {
    "masuda_id": "20200314084505",
    "title": "anond:20200314084142",
    "content": "名詞の名詞を食べる名詞なんているの？",
    "bookmark_count": 0,
    "category": null
  },
  {
    "masuda_id": "20200314084443",
    "title": "anond:20200314084129",
    "content": "名詞は名詞なのに慰められたくて名詞名詞だと思い込んでるだけだ",
    "bookmark_count": 0,
    "category": null
  },
  {
    "masuda_id": "20200314084404",
    "title": "anond:20200314083827",
    "content": "でも名詞は名詞名詞から。",
    "bookmark_count": 0,
    "category": null
  },
  {
    "masuda_id": "20200314084322",
    "title": "anond:20200314084220",
    "content": "名詞名詞だから名詞はそもそもいらない名詞じゃない？",
    "bookmark_count": 0,
    "category": null
  },
  {
    "masuda_id": "20200314084248",
    "title": "anond:20200314084105",
    "content": "名詞にとっては名詞だろうね",
    "bookmark_count": 0,
    "category": null
  }
]