[
  {
    "masuda_id": "20200215123911",
    "title": "コロナウィルスへの特効薬が生まれたら ",
    "content": "名詞には名詞で名詞名詞と名詞名詞を出すになる名詞だろうか。名詞の名詞名詞は名詞名詞で、名詞名詞の名詞は名詞名詞名詞も含めて名詞で治る。だが名詞と名詞が名詞になるから名詞は名詞では出さない名詞にする名詞が形容詞とは言われる。しかし名詞名詞して、名詞の名詞にかかったら名詞名詞の名詞だと言われ名詞をもらってすぐ治る。でも名詞の名詞は名詞だと名詞されてしまう。よって名詞にも名詞がとりあえず出される。名詞名詞名詞が名詞名詞だけかもしれないし、しっかり休んでたら名詞名詞名詞も治ったかもしれないのに。名詞の名詞名詞名詞は名詞名詞。名詞の名詞も含めた名詞に形容詞名詞できる名詞が生まれれば、名詞名詞名詞にも効く名詞が出てくる名詞になる。名詞の名詞な名詞が来た名詞名詞名詞が名詞名詞されない名詞に、名詞名詞がホイホイ名詞される名詞が来る名詞かもしれない。名詞名詞名詞名詞も出てくるかもしれないだろう。名詞な名詞に備える名詞に名詞名詞を名詞の名詞にホイホイ使うなと言われてても名詞されるかもしれない。しかも名詞が切れていないし名詞も形容詞から名詞の名詞名詞だったとしても。",
    "bookmark_count": 0,
    "category": null
  },
  {
    "masuda_id": "20200215123904",
    "title": "anond:20200215112549",
    "content": "「あの名詞の名詞」ではありません。あの名詞な名詞の名詞名詞は、名詞を見て名詞している名詞を名詞させるから名詞な名詞です。",
    "bookmark_count": 0,
    "category": null
  },
  {
    "masuda_id": "20200215123841",
    "title": "anond:20200215123555",
    "content": "名詞した名詞だろ",
    "bookmark_count": 0,
    "category": null
  },
  {
    "masuda_id": "20200215123754",
    "title": "anond:20200215123353",
    "content": "名詞な",
    "bookmark_count": 0,
    "category": null
  },
  {
    "masuda_id": "20200215123655",
    "title": "anond:20200215120359",
    "content": "名詞な名詞をする名詞と、名詞の名詞名詞は違うかな。",
    "bookmark_count": 0,
    "category": null
  },
  {
    "masuda_id": "20200215123642",
    "title": "anond:20200215123434",
    "content": "名詞ごときで騒ぐ名詞もねーだろ名詞なんて名詞を出す名詞もねーだろ名詞に名詞する名詞は名詞にもねえし",
    "bookmark_count": 0,
    "category": null
  },
  {
    "masuda_id": "20200215123555",
    "title": "anond:20200215123434",
    "content": "名詞名詞の名詞",
    "bookmark_count": 0,
    "category": null
  },
  {
    "masuda_id": "20200215123511",
    "title": "anond:20200215123353",
    "content": "名詞",
    "bookmark_count": 0,
    "category": null
  },
  {
    "masuda_id": "20200215123434",
    "title": "ライブハウスで痴漢が有ったんだけども ",
    "content": "某名詞に名詞で名詞にも名詞した名詞の名詞で名詞が名詞した名詞だわ。しかも名詞触られたとかじゃなく名詞名詞の名詞当然名詞は名詞、名詞の名詞の名詞からも憤りを感じる名詞とかがあった名詞だが形容詞名詞になる名詞があった名詞だ。名詞、名詞の名詞持ってて名詞名詞か同じ名詞が名詞って名詞がいるけど、その名詞の名詞がその名詞に行って名詞だよね。名詞、名詞はかなり名詞名詞だけど名詞が名詞な名詞の名詞で名詞が名詞した名詞は名詞名詞突っ込んでくる名詞な名詞だけど、名詞の名詞については名詞も形容詞たかの名詞に触れて名詞だわ。名詞の名詞が名詞って名詞でも形容詞て、名詞かが名詞の名詞が名詞を名詞まで引っ張ってきてる名詞を名詞した名詞も名詞かいる名詞だわ。そもそも名詞までの名詞って形容詞たから、名詞が名詞とする名詞な名詞だった名詞だわ。「名詞は名詞に形容詞名詞！」と名詞で思ってい名詞な名詞なのになあ…名詞の名詞な名詞でこういう名詞があったら名詞名詞な名詞だけどなあ…と思っていた名詞だけどさ…まさかな…名詞名詞名詞か経ったけど、未だに触れる名詞は形容詞相変わらず名詞な名詞をしてるらしいそもそも書き込む名詞が名詞名詞て名詞にしてる名詞だけども名詞も形容詞から決めつける名詞では形容詞が…名詞だろうな、この名詞は…名詞の名詞が名詞の名詞である名詞を祈るよ",
    "bookmark_count": 0,
    "category": null
  },
  {
    "masuda_id": "20200215123416",
    "title": "anond:20200215123335",
    "content": "名詞じゃねーか名詞",
    "bookmark_count": 0,
    "category": null
  },
  {
    "masuda_id": "20200215123353",
    "title": "anond:20200215123239",
    "content": "名詞って名詞な名詞か知らん名詞？",
    "bookmark_count": 0,
    "category": null
  },
  {
    "masuda_id": "20200215123335",
    "title": "anond:20200215123015",
    "content": "名詞！名詞！名詞！　名詞名詞",
    "bookmark_count": 0,
    "category": null
  },
  {
    "masuda_id": "20200215123239",
    "title": "anond:20200215111804",
    "content": "名詞より名詞の名詞が名詞なら名詞だけ言えば形容詞だろ。名詞名詞だと、名詞・名詞・名詞・名詞。",
    "bookmark_count": 0,
    "category": null
  },
  {
    "masuda_id": "20200215123154",
    "title": "anond:20200214205758",
    "content": "名詞に名詞できる名詞って名詞だけおる名詞か名詞名詞はあげた名詞に名詞やんけ名詞が！っていう名詞かける名詞けど",
    "bookmark_count": 0,
    "category": null
  },
  {
    "masuda_id": "20200215123152",
    "title": "日本で感染者を増やさないためにできること ",
    "content": "名詞が名詞名詞すれば名詞は増えない名詞で名詞",
    "bookmark_count": 0,
    "category": null
  },
  {
    "masuda_id": "20200215123015",
    "title": "anond:20200215120359",
    "content": "そもそも名詞は名詞・名詞じゃねえ。名詞だ。",
    "bookmark_count": 0,
    "category": null
  },
  {
    "masuda_id": "20200215123009",
    "title": "anond:20200215121900",
    "content": "名詞ぶちまけて名詞名詞名詞はよく見るけどまだ生きてる名詞は形容詞な名詞名詞とかあったら名詞くらいなら送りつけたい",
    "bookmark_count": 0,
    "category": null
  },
  {
    "masuda_id": "20200215122909",
    "title": "anond:20200215120343",
    "content": "別に名詞名詞とか名詞名詞に名詞見る名詞は名詞あるだろ。名詞は名詞に名詞の名詞着てもらうとか。",
    "bookmark_count": 0,
    "category": null
  },
  {
    "masuda_id": "20200215122751",
    "title": "anond:20200215121755",
    "content": "どう名詞も形容詞。名詞名詞名詞だと名詞名詞でも名詞わ形容詞。",
    "bookmark_count": 0,
    "category": null
  },
  {
    "masuda_id": "20200215122658",
    "title": "anond:20200215121818",
    "content": "名詞に対する名詞の名詞かな。名詞の名詞は名詞で名詞かといえば名詞だけど、名詞では名詞は名詞で名詞にのって楽しむ名詞だから形容詞名詞な名詞は名詞されるとかそういう名詞かと思った。名詞だけ形容詞て名詞名詞とか名詞じゃねとか思ったり。",
    "bookmark_count": 0,
    "category": null
  },
  {
    "masuda_id": "20200215122630",
    "title": "anond:20200215120654",
    "content": "＞名詞をしているとはいえ名詞は名詞に名詞を名詞していたし、名詞で名詞に名詞をかけ名詞な名詞は、名詞そう言う名詞だ。「名詞に名詞していた名詞なのに」と。",
    "bookmark_count": 0,
    "category": null
  },
  {
    "masuda_id": "20200215122627",
    "title": "anond:20200215121638",
    "content": "名詞は　名詞名詞の名詞が名詞やで。",
    "bookmark_count": 0,
    "category": null
  },
  {
    "masuda_id": "20200215122612",
    "title": "プログラミングスクール界隈 ",
    "content": "名詞とか名詞の名詞の名詞名詞に名詞される名詞名詞(名詞名詞)をやっている名詞ではないだろうか。そんな名詞がする。名詞、名詞、名詞、名詞名詞などなど、名詞は名詞名詞",
    "bookmark_count": 0,
    "category": null
  },
  {
    "masuda_id": "20200215122550",
    "title": "anond:20200215120446",
    "content": "名詞で、名詞の名詞が形容詞と思ってます。",
    "bookmark_count": 0,
    "category": null
  },
  {
    "masuda_id": "20200215122506",
    "title": "anond:20200215120446",
    "content": "名詞の名詞の名詞が名詞と名詞で名詞名詞で休んでるから名詞も名詞してる名詞やで",
    "bookmark_count": 0,
    "category": null
  }
]