[
  {
    "masuda_id": "20200311192116",
    "title": "経産省「あなたが買い叩いているのはこの国の未来だ！」 ",
    "content": "いや名詞名詞に回る名詞の名詞を名詞して名詞名詞な名詞を名詞名詞して名詞に捨ててきた名詞が名詞名詞名詞だろ。名詞みて名詞に名詞に名詞してる名詞も名詞というか名詞というかもうちょっと形容詞ならないと名詞までも買い叩かれる名詞の名詞だぞ。名詞://名詞名詞/名詞_名詞名詞/名詞?名詞=名詞",
    "bookmark_count": 0,
    "category": null
  },
  {
    "masuda_id": "20200311192106",
    "title": "疫病の戦略",
    "content": "つらつら考えた名詞名詞の名詞名詞は、名詞の名詞が名詞名詞名詞してる名詞で名詞した名詞がもし名詞名詞なら、無名詞の名詞も名詞まで形容詞名詞に名詞を名詞撒く名詞は出来なかっただろう名詞に名詞なんかを通じてある程度名詞した名詞だろうか？それでも、名詞や名詞を越えて名詞名詞を広げる名詞は形容詞たに名詞ないそう考えると、名詞この名詞で名詞に名詞する名詞を得た新名詞は、名詞形容詞名詞やったと言えるかもしれない名詞を名詞と名詞名詞なら、名詞の名詞はもっとずっと上がるだろう名詞や名詞などは今や名詞と名詞名詞名詞へでも行き得るが、名詞には名詞名詞の名詞名詞＝名詞の名詞名詞な名詞名詞な名詞だそう考えると、名詞は形容詞ある名詞から名詞の名詞へと名詞を名詞名詞か乗り継げば、かなり名詞で名詞くらいは名詞でき名詞だ名詞名詞の形容詞名詞というなら、名詞はどうだろう？形容詞調べてみたが、名詞の名詞での名詞はあるものの、名詞名詞での同名詞の名詞という名詞は見つけられない名詞を介して名詞するなら名詞にはかなり形容詞名詞な名詞を持つが、案外名詞まででも形容詞名詞か、単に名詞の名詞での名詞は名詞が形容詞て追い切れていない名詞かでは名詞にほとんど名詞しない名詞、たとえば名詞を名詞にした名詞、名詞はどうする名詞か？名詞またざっと調べた名詞、名詞な名詞や名詞名詞を介したり、親名詞から名詞へ名詞や名詞を通じて名詞したり、傷ついた名詞名詞の名詞を介して名詞したり（名詞や、名詞に踏まれたり齧られたり名詞だろう）するらしい名詞の名詞名詞は名詞名詞の名詞だけではないだろうが、名詞という名詞だけで見ても、名詞に合わせて名詞な名詞がある名詞だ名詞って形容詞ね",
    "bookmark_count": 1,
    "category": null
  },
  {
    "masuda_id": "20200311192100",
    "title": "anond:20200311191807",
    "content": "名詞！名詞！名詞！名詞！名詞！",
    "bookmark_count": 0,
    "category": null
  },
  {
    "masuda_id": "20200311191932",
    "title": "anond:20200311191823",
    "content": "どうせ溶かすなら名詞にくれれば形容詞たのに",
    "bookmark_count": 0,
    "category": null
  },
  {
    "masuda_id": "20200311191826",
    "title": "anond:20200311191615",
    "content": "名詞もかれも名詞の名詞に形容詞名詞に話してるけど実際は名詞名詞にでてる名詞より名詞な名詞だろうなって思うと名詞が浮かぶ",
    "bookmark_count": 0,
    "category": null
  },
  {
    "masuda_id": "20200311191823",
    "title": "株で1000万溶けた ",
    "content": "名詞で名詞に吹っ飛んだ名詞もあるけど、名詞で持ってる名詞は名詞も名詞すれば戻ると思うし、下がった名詞に名詞を名詞の形容詞名詞に切り替えたので実際はもう少し形容詞済むとは思うがひたすら形容詞",
    "bookmark_count": 0,
    "category": null
  },
  {
    "masuda_id": "20200311191807",
    "title": "anond:20200311191731",
    "content": "名詞は名詞名詞名詞な名詞だと思え名詞思っていても名詞に名詞は名詞でない",
    "bookmark_count": 0,
    "category": null
  },
  {
    "masuda_id": "20200311191804",
    "title": "anond:20200311191658",
    "content": "名詞です",
    "bookmark_count": 0,
    "category": null
  },
  {
    "masuda_id": "20200311191745",
    "title": "気が利く奴が大嫌い ",
    "content": "名詞名詞な名詞が利かない名詞を見下したり名詞するから本当に名詞な名詞だよ",
    "bookmark_count": 0,
    "category": null
  },
  {
    "masuda_id": "20200311191733",
    "title": "[ファクトチェック]GWには東京ビックサイトでコロナまつりが開かれるってマ？ ",
    "content": "名詞名詞　名詞で罹れば　死ぬ名詞も形容詞ない　を名詞で行く名詞って名詞？",
    "bookmark_count": 0,
    "category": null
  },
  {
    "masuda_id": "20200311191731",
    "title": "anond:20200311191045",
    "content": "名詞で名詞",
    "bookmark_count": 0,
    "category": null
  },
  {
    "masuda_id": "20200311191658",
    "title": "",
    "content": "もう名詞だけで名詞名詞超えてる名詞だけど、名詞名詞で死ぬって名詞は名詞なの？その名詞の名詞は名詞形容詞？",
    "bookmark_count": 0,
    "category": null
  },
  {
    "masuda_id": "20200311191650",
    "title": "anond:20200311092256",
    "content": "名詞形容詞名詞が流行ってると名詞つく名詞は名詞の名詞なのでなるべく名詞を形容詞とろう。そして名詞をいっぱい浴びよう。",
    "bookmark_count": 0,
    "category": null
  },
  {
    "masuda_id": "20200311191649",
    "title": "",
    "content": "しかし名詞の名詞が分からない名詞だから、既に育ってしまった名詞よりは名詞あるで",
    "bookmark_count": 0,
    "category": null
  },
  {
    "masuda_id": "20200311191634",
    "title": "anond:20200311190343",
    "content": "名詞だ名詞",
    "bookmark_count": 0,
    "category": null
  },
  {
    "masuda_id": "20200311191615",
    "title": "自粛延長は仕方ない ",
    "content": "と名詞が名詞してるけど、別に名詞する名詞も形容詞けどそんな名詞ないと思えるほどの名詞がある名詞か？　名詞、こういう名詞の名詞には名詞やべ名詞やべ名詞って言っておいて名詞だ名詞だの名詞の名詞には名詞名詞、名詞クってる名詞は名詞名詞名詞な名詞になる名詞が形容詞名詞な名詞だけど",
    "bookmark_count": 0,
    "category": null
  },
  {
    "masuda_id": "20200311191555",
    "title": "anond:20200311143205",
    "content": "×名詞名詞だけど名詞ない○名詞名詞で名詞",
    "bookmark_count": 0,
    "category": null
  },
  {
    "masuda_id": "20200311191551",
    "title": "入れたら3秒でイクようなオナホ教えろ ",
    "content": "名詞なら名詞で名詞！",
    "bookmark_count": 0,
    "category": null
  },
  {
    "masuda_id": "20200311191538",
    "title": "anond:20200311191057",
    "content": "やっぱ生まれてすぐは形容詞ない名詞か",
    "bookmark_count": 0,
    "category": null
  },
  {
    "masuda_id": "20200311191407",
    "title": "今年はジャパンレプタイルズショー行かなかったわ ",
    "content": "やっぱり名詞には移りたくないしね",
    "bookmark_count": 0,
    "category": null
  },
  {
    "masuda_id": "20200311191345",
    "title": "小ネタ",
    "content": "名詞を走ってた名詞に名詞名詞の名詞が貼ってあって、思わず笑ってしまったけど、こんな名詞通じる名詞名詞いんだよと思った",
    "bookmark_count": 0,
    "category": null
  },
  {
    "masuda_id": "20200311191331",
    "title": "anond:20200311191045",
    "content": "名詞名詞に名詞だからなぁ名詞の名詞では名詞ある名詞もあるだろうから名詞は形容詞ないが・・・名詞に名詞が追いついてないだけも名詞ある",
    "bookmark_count": 0,
    "category": null
  },
  {
    "masuda_id": "20200311191147",
    "title": "anond:20200311191123",
    "content": "名詞被りは？",
    "bookmark_count": 0,
    "category": null
  },
  {
    "masuda_id": "20200311191131",
    "title": "anond:20200311190745",
    "content": "チラッと見た名詞だと名詞より名詞名詞は増えているけど名詞名詞名詞じゃないか名詞名詞によって名詞くらいは変わる名詞くらいなら名詞名詞や名詞で押し通せるで？",
    "bookmark_count": 0,
    "category": null
  },
  {
    "masuda_id": "20200311191128",
    "title": "anond:20200311190444",
    "content": "名詞！名詞！名詞！名詞！名詞！",
    "bookmark_count": 0,
    "category": null
  }
]