[
  {
    "masuda_id": "20200129144918",
    "title": "",
    "content": "名詞の名詞を伴ってる名詞に、「名詞も名詞名詞名詞に患ってね、名詞」名詞から名詞がひたすら名詞に堪えてるのに、名詞の名詞名詞など名詞まずは名詞が第一だ",
    "bookmark_count": 0,
    "category": null
  },
  {
    "masuda_id": "20200129144835",
    "title": "anond:20200129144619",
    "content": "名詞は名詞が名詞で名詞かも名詞で",
    "bookmark_count": 0,
    "category": null
  },
  {
    "masuda_id": "20200129144831",
    "title": "anond:20200129144157",
    "content": "名詞の名詞やった名詞やね",
    "bookmark_count": 0,
    "category": null
  },
  {
    "masuda_id": "20200129144816",
    "title": "小野ほりでいの何が良いんだ？ ",
    "content": "名詞な名詞を形容詞名詞に言ってるだけにしか読めない名詞だけど名詞名詞は大名詞している。名詞が名詞な名詞か名詞が名詞な名詞か。",
    "bookmark_count": 0,
    "category": null
  },
  {
    "masuda_id": "20200129144810",
    "title": "anond:20200129143702",
    "content": "まだ名詞が形容詞て名詞して叩いて形容詞かわからないだけ名詞に形容詞名詞言って名詞が名詞な名詞の名詞だったりしたら名詞名詞食らうからな",
    "bookmark_count": 0,
    "category": null
  },
  {
    "masuda_id": "20200129144753",
    "title": "anond:20200129144532",
    "content": "名詞も名詞の名詞を忘れへんで",
    "bookmark_count": 0,
    "category": null
  },
  {
    "masuda_id": "20200129144619",
    "title": "anond:20200129143927",
    "content": "名詞がごっそり名詞に行った名詞から来る名詞名詞だと思う形容詞名詞の名詞の入り名詞って名詞で名詞とか名詞だよいまどき名詞じゃねえの？",
    "bookmark_count": 0,
    "category": null
  },
  {
    "masuda_id": "20200129144549",
    "title": "武漢でたかだか多く見積もっても10000人しか感染してない筈の感染症に、700/1100万でしかない日本人が5人以上感染してるっぽいのは何故？ ",
    "content": "名詞は名詞にかかり形容詞から？",
    "bookmark_count": 0,
    "category": null
  },
  {
    "masuda_id": "20200129144540",
    "title": "anond:20200129144421",
    "content": "名詞の名詞は名詞やで",
    "bookmark_count": 0,
    "category": null
  },
  {
    "masuda_id": "20200129144532",
    "title": "anond:20200128160337",
    "content": "「名詞の名詞に形容詞ない名詞について」多分名詞を名詞に名詞に名詞されて名詞名詞から消えた名詞だろうな。名詞した名詞は恐らく名詞:名詞憤り名詞が名詞だしとにかく名詞。",
    "bookmark_count": 0,
    "category": null
  },
  {
    "masuda_id": "20200129144457",
    "title": "御堂筋線ホー厶のレイプ犯、「無敵の人」だったんだな ",
    "content": "名詞だってさ。どーせ名詞名詞していくだけなら名詞名詞名詞で名詞を名詞しまくってやる、って名詞か名詞がいる名詞はこんな名詞で名詞育てる名詞形容詞ない名詞かな。名詞は名詞だけである名詞形容詞た名詞かな",
    "bookmark_count": 0,
    "category": null
  },
  {
    "masuda_id": "20200129144434",
    "title": "anond:20200129143927",
    "content": "名詞は名詞に名詞られたで",
    "bookmark_count": 0,
    "category": null
  },
  {
    "masuda_id": "20200129144421",
    "title": "anond:20200129143926",
    "content": "名詞まさに名詞すべきは名詞より名詞より名詞した名詞名詞名詞の名詞だけどな…",
    "bookmark_count": 0,
    "category": null
  },
  {
    "masuda_id": "20200129144342",
    "title": "anond:20200129143702",
    "content": "名詞されてる名詞だから名詞名詞に名詞名詞名詞も言えないだけだぞ名詞名詞で殴られるからな",
    "bookmark_count": 0,
    "category": null
  },
  {
    "masuda_id": "20200129144336",
    "title": "anond:20200129144203",
    "content": "名詞〜名詞名詞",
    "bookmark_count": 0,
    "category": null
  },
  {
    "masuda_id": "20200129144334",
    "title": "焼き鳥性格診断 ",
    "content": "名詞:名詞名詞・・・超名詞。名詞の言う名詞は「名詞もあるよね」と言いつつ、名詞が名詞。つくね・・・名詞。名詞から名詞まで名詞名詞。名詞が形容詞ば名詞は名詞でも形容詞だろうと言う名詞。正名詞・・・名詞。名詞さえあれば名詞など要らぬ。形容詞は名詞だけど、名詞も名詞名詞も名詞名詞と思ってる。名詞・・・ちょい変わり名詞。少し名詞と比べると浮いてる。でも頭抜けた名詞ってほどではない。せせり・・・名詞。形容詞。惚れれば名詞でも名詞でもすぐ合わせてしまう。名詞。形容詞言うと名詞。でもカラッとしてるのであまり嫌われない。名詞・・・名詞。名詞。名詞があると言うより名詞。名詞が付いて名詞名詞する名詞もある。名詞（名詞）・・・名詞。名詞が名詞でガツガツしてる。名詞名詞が形容詞。名詞名詞・・・名詞。名詞名詞していると滅多に見ない。名詞で形容詞らしい。名詞・・・名詞。名詞が来ても動じない。あんまり名詞まで形容詞なる名詞はない。名詞・・・名詞。名詞にあまり好かれないけど、形容詞名詞は名詞される。名詞が形容詞と形容詞。名詞・・・名詞。名詞名詞。名詞で形容詞。意外と名詞と名詞が合う名詞。名詞・・・名詞。名詞名詞の名詞が名詞なんて、名詞しかいねえよ。かわ・・・名詞。名詞名詞抜けない。しっかり焼いて名詞いれよう。名詞・・・名詞読めない。名詞から選ぶという名詞さえできない名詞の読めな名詞。名詞名詞名詞・・・名詞。名詞で名詞に狙った名詞を落とす。名詞の名詞が形容詞。名詞名詞・・・名詞。名詞名詞、ひょろひょろしてる。",
    "bookmark_count": 0,
    "category": null
  },
  {
    "masuda_id": "20200129144333",
    "title": "anond:20200129143418",
    "content": "名詞ʃ名詞ʊ名詞ə名詞ɪ名詞",
    "bookmark_count": 0,
    "category": null
  },
  {
    "masuda_id": "20200129144316",
    "title": "anond:20200129144048",
    "content": "名詞が名詞名詞な名詞は名詞やで",
    "bookmark_count": 0,
    "category": null
  },
  {
    "masuda_id": "20200129144203",
    "title": "anond:20200129144042",
    "content": "は名詞",
    "bookmark_count": 0,
    "category": null
  },
  {
    "masuda_id": "20200129144158",
    "title": "anond:20200129143310",
    "content": "名詞少しずつくる名詞で、生きる名詞を名詞に名詞する名詞の名詞やぞ。「名詞と名詞」とかそういう名詞で名詞を言うな。",
    "bookmark_count": 0,
    "category": null
  },
  {
    "masuda_id": "20200129144157",
    "title": "anond:20200129144042",
    "content": "なんで名詞の名詞やねーん名詞！て突っ込む名詞が形容詞で",
    "bookmark_count": 0,
    "category": null
  },
  {
    "masuda_id": "20200129144107",
    "title": "anond:20200129102823",
    "content": "名詞も名詞探して名詞へ名詞へ",
    "bookmark_count": 0,
    "category": null
  },
  {
    "masuda_id": "20200129144048",
    "title": "anond:20200129143702",
    "content": "そもそも名詞として取り上げられて名詞じゃないの名詞貼ってよ",
    "bookmark_count": 0,
    "category": null
  },
  {
    "masuda_id": "20200129144042",
    "title": "anond:20200129085117",
    "content": "名詞に「名詞名詞が名詞？名詞は名詞な名詞だけど」って言われてじ名詞の名詞を言う名詞は名詞形容詞。名詞が名詞している名詞は、「名詞」に決まっとるやろ。名詞が合いますね。じゃあ名詞名詞に名詞にという名詞を読まなきゃ。",
    "bookmark_count": 0,
    "category": null
  },
  {
    "masuda_id": "20200129143935",
    "title": "anond:20200129143735",
    "content": "名詞はいつも名詞は名詞やで",
    "bookmark_count": 0,
    "category": null
  }
]