[
  {
    "masuda_id": "20200203120155",
    "title": "anond:20200203120017",
    "content": "名詞名詞は名詞を取りたい！",
    "bookmark_count": 0,
    "category": null
  },
  {
    "masuda_id": "20200203120130",
    "title": "anond:20200203111833",
    "content": "じゃあしゃぶれよ",
    "bookmark_count": 0,
    "category": null
  },
  {
    "masuda_id": "20200203120128",
    "title": "そういや宇崎ちゃんのアレって2ページ漫画で裏にもあるみたいだけど ",
    "content": "名詞名詞は名詞もちゃんと名詞してから言ってる名詞だろうか・・・また名詞クルクル名詞になったり名詞？",
    "bookmark_count": 0,
    "category": null
  },
  {
    "masuda_id": "20200203120114",
    "title": "",
    "content": "名詞を名詞に名詞が形容詞形容詞名詞になった名詞にさ、騒ぐ名詞によって「言われてみるとそう名詞」って名詞も増える名詞だよな",
    "bookmark_count": 0,
    "category": null
  },
  {
    "masuda_id": "20200203120035",
    "title": "anond:20200203115807",
    "content": "名詞になった名詞に名詞名詞が保てる名詞か？保てるなら名詞名詞いる名詞＋名詞名詞の名詞が見込める名詞だから盛り上がるだろうが…",
    "bookmark_count": 0,
    "category": null
  },
  {
    "masuda_id": "20200203120017",
    "title": "anond:20200203115233",
    "content": "名詞に名詞の名詞は名詞形容詞な。じゃあ名詞に名詞に名詞の名詞に名詞してるのに、態々名詞で名詞とかする名詞って名詞だろ。名詞に名詞してるのに、態々名詞名詞に戻ってきて名詞する名詞ってやっぱ名詞じゃないかと思う。",
    "bookmark_count": 0,
    "category": null
  },
  {
    "masuda_id": "20200203115902",
    "title": "anond:20200203115503",
    "content": "名詞よりは名詞を読んでるけど「名詞よりも名詞がある」と名詞する名詞はさすがに名詞だと思うよ。",
    "bookmark_count": 0,
    "category": null
  },
  {
    "masuda_id": "20200203115807",
    "title": "としまえん",
    "content": "名詞で潰されると分かって名詞に名詞言ってる名詞が形容詞な形容詞か、名詞の名詞は名詞名詞で名詞名詞に使っている名詞が名詞な名詞だよ。名詞だぞ？名詞で。名詞名詞。でも名詞したら悩む名詞形容詞名詞しない名詞は名詞名詞で盛り上がるが、名詞は形容詞名詞もあったし名詞名詞。名詞名詞の名詞と名詞くらいか？盛り上がるの。名詞はごく名詞の名詞が名詞名詞から名詞やめて形容詞名詞名詞の名詞名詞としては、名詞の名詞と名詞になる名詞は名詞に形容詞。名詞は悲しむかもしれないけど、名詞とかは残す名詞名詞だし、名詞名詞に名詞が戻ってくれれば何より名詞で名詞～名詞しか行ってない名詞な名詞を名詞に名詞とか言ってる名詞じゃない。名詞は名詞名詞してるぞ。名詞だけど形容詞ても形容詞かな？が名詞の名詞",
    "bookmark_count": 0,
    "category": null
  },
  {
    "masuda_id": "20200203115757",
    "title": "",
    "content": "名詞の名詞とか名詞出す名詞は形容詞けどそれで名詞っていう名詞はどうな名詞だろ",
    "bookmark_count": 0,
    "category": null
  },
  {
    "masuda_id": "20200203115740",
    "title": "",
    "content": "名詞名詞って「名詞を洗おうか」を形容詞言った名詞な名詞じゃね？名詞をしていて気づいた名詞だ。",
    "bookmark_count": 0,
    "category": null
  },
  {
    "masuda_id": "20200203115526",
    "title": "anond:20200202120130",
    "content": "名詞名詞（言いたいだけ）",
    "bookmark_count": 1,
    "category": null
  },
  {
    "masuda_id": "20200203115503",
    "title": "anond:20200203114816",
    "content": "名詞が名詞読んだ名詞形容詞だけじゃね。名詞名詞だ名詞だと言われる名詞から名詞名詞に名詞な名詞出してきた名詞が名詞だが。",
    "bookmark_count": 0,
    "category": null
  },
  {
    "masuda_id": "20200203115446",
    "title": "anond:20200203114621",
    "content": "名詞の名詞が形容詞から",
    "bookmark_count": 0,
    "category": null
  },
  {
    "masuda_id": "20200203115437",
    "title": "anond:20200203114621",
    "content": "あの名詞は名詞にだけ名詞する。",
    "bookmark_count": 0,
    "category": null
  },
  {
    "masuda_id": "20200203115256",
    "title": "",
    "content": "抜けるかどうかで言うなら名詞名詞とかの名詞がよっぽど抜けるけども",
    "bookmark_count": 0,
    "category": null
  },
  {
    "masuda_id": "20200203115233",
    "title": "anond:20200203114957",
    "content": "名詞の名詞で名詞形容詞名詞名詞名詞かいるけど、態々名詞がどうで名詞が形容詞とかそんな話してこないわ。",
    "bookmark_count": 0,
    "category": null
  },
  {
    "masuda_id": "20200203115232",
    "title": "anond:20200203114512",
    "content": "名詞は、大きな名詞に名詞する名詞の名詞な名詞だ。だから、名詞とか名詞名詞に分かり形容詞名詞をつけてあげないと、「名詞、名詞」って名詞が抑えられない。「名詞」だけを見せられると疼きが収まらない。",
    "bookmark_count": 0,
    "category": null
  },
  {
    "masuda_id": "20200203115229",
    "title": "anond:20200203114816",
    "content": "名詞が形容詞ので名詞くらい名詞名詞にやらないと「名詞名詞な名詞」を名詞できない。",
    "bookmark_count": 0,
    "category": null
  },
  {
    "masuda_id": "20200203115220",
    "title": "anond:20200203115026",
    "content": "「名詞な名詞の名詞を名詞が名詞する」という名詞が取れていた名詞が、名詞でもう一気に名詞になった名詞なそんな名詞の名詞なんて実際ろくな名詞じゃない、という名詞も名詞も形容詞名詞がこうも知れ渡ってしまうと",
    "bookmark_count": 0,
    "category": null
  },
  {
    "masuda_id": "20200203115051",
    "title": "anond:20200203114705",
    "content": "名詞名詞の名詞名詞ですら、名詞の名詞が名詞でないとそういう名詞では形容詞た。いや名詞名詞だったからこそかな、名詞は。名詞には名詞名詞とか名詞名詞だ。だから名詞でもコロコロ名詞名詞の名詞に名詞名詞が名詞になるし。",
    "bookmark_count": 0,
    "category": null
  },
  {
    "masuda_id": "20200203115033",
    "title": "anond:20200203115006",
    "content": "名詞は？",
    "bookmark_count": 0,
    "category": null
  },
  {
    "masuda_id": "20200203115026",
    "title": "社会運動（）",
    "content": "名詞を名詞して名詞とか名詞なんかに名詞しつつ名詞名詞名詞が名詞名詞すると、名詞した名詞の名詞を名詞して名詞した名詞を名詞できるけど、名詞なんかだと名詞の名詞が名詞名詞される名詞、名詞名詞には名詞を名詞して名詞名詞減らすか、名詞せずに名詞名詞に名詞名詞だ名詞だ名詞の名詞を受けるかの名詞が名詞になる。",
    "bookmark_count": 0,
    "category": null
  },
  {
    "masuda_id": "20200203115022",
    "title": "anond:20200203113504",
    "content": "おせえよ",
    "bookmark_count": 0,
    "category": null
  },
  {
    "masuda_id": "20200203115006",
    "title": "anond:20200203114512",
    "content": "名詞も「あの名詞が抜けるから名詞」なんて言ってない。「名詞名詞を名詞する」から名詞だと言ってる。名詞名詞も、名詞を名詞すると言う名詞も、名詞の名詞の名詞で名詞の名詞も名詞も名詞してないけど。",
    "bookmark_count": 0,
    "category": null
  },
  {
    "masuda_id": "20200203114957",
    "title": "anond:20200203113450",
    "content": "「名詞の名詞を名詞名詞する名詞」って、名詞にとって名詞で名詞する名詞は名詞な名詞では形容詞名詞か…？",
    "bookmark_count": 0,
    "category": null
  }
]