[
  {
    "masuda_id": "20200131175523",
    "title": "高学歴の悟空",
    "content": "名詞名詞で名詞通って、け名詞名詞のけ名詞名詞受かったぞ！",
    "bookmark_count": 0,
    "category": null
  },
  {
    "masuda_id": "20200131175506",
    "title": "anond:20200131175413",
    "content": "名詞払いできたな名詞で名詞してくれれば",
    "bookmark_count": 0,
    "category": null
  },
  {
    "masuda_id": "20200131175451",
    "title": "anond:20200131155001",
    "content": "「そうだね。お取り替えだね。」という名詞ではなかろうか",
    "bookmark_count": 0,
    "category": null
  },
  {
    "masuda_id": "20200131175445",
    "title": "みんな普通にセックスしてますよね？ ",
    "content": "名詞の名詞が出る名詞に思う名詞だが名詞名詞名詞名詞名詞の名詞は形容詞ても名詞でも名詞に名詞名詞～名詞名詞は名詞してる名詞だよね？名詞は名詞名詞名詞名詞、名詞名詞〜名詞名詞名詞してるのであまりにも名詞が名詞になっている名詞ですけど、名詞の名詞の名詞もそうですよね？",
    "bookmark_count": 0,
    "category": null
  },
  {
    "masuda_id": "20200131175441",
    "title": "anond:20200131175342",
    "content": "名詞の名詞に見てもらうという名詞と名詞名詞は違う。",
    "bookmark_count": 0,
    "category": null
  },
  {
    "masuda_id": "20200131175342",
    "title": "",
    "content": "名詞をしないという名詞に名詞を名詞する名詞は名詞ではない。名詞名詞。名詞の名詞に見てもらうという名詞と名詞名詞は違う。名詞:名詞",
    "bookmark_count": 0,
    "category": null
  },
  {
    "masuda_id": "20200131175313",
    "title": "",
    "content": "名詞に対して名詞の名詞とか名詞名詞名詞だけど名詞は形容詞名詞やなあ",
    "bookmark_count": 0,
    "category": null
  },
  {
    "masuda_id": "20200131175309",
    "title": "anond:20200131172729",
    "content": "名詞には名詞名詞な名詞もいる名詞から、名詞の名詞に名詞させる名詞は形容詞だろう。名詞はやはり、名詞名詞名詞名詞な名詞な名詞に名詞してもらう名詞が形容詞。",
    "bookmark_count": 0,
    "category": null
  },
  {
    "masuda_id": "20200131175241",
    "title": "anond:20200131121743",
    "content": "名詞？名詞？",
    "bookmark_count": 0,
    "category": null
  },
  {
    "masuda_id": "20200131175056",
    "title": "はてな民は子供にもどった方がいい ",
    "content": "名詞名詞がどんなに名詞名詞に張り付いたって名詞名詞も名詞は変わらない名詞なんて名詞にせず名詞の名詞名詞にやりたい名詞やれよその名詞がよっぽど名詞になれる名詞なんて名詞の名詞を名詞してなくしましょうっていう名詞名詞な名詞だから名詞名詞が名詞に行かなくても名詞名詞名詞も変わってないだろ名詞という名詞は名詞の名詞では名詞の名詞の名詞名詞な名詞名詞にしたって名詞形容詞名詞だよ",
    "bookmark_count": 0,
    "category": null
  },
  {
    "masuda_id": "20200131175052",
    "title": "anond:20200131174319",
    "content": "もしかして名詞って名詞だけだと思ってる？名詞はあくまで名詞の名詞の名詞であって名詞名詞な名詞と名詞だけ名詞するかは名詞によるが。（名詞がどの名詞でやってる名詞かは知らんが）",
    "bookmark_count": 0,
    "category": null
  },
  {
    "masuda_id": "20200131175028",
    "title": "",
    "content": "名詞でこんだけ盛り上がる名詞形容詞よなあやっぱ名詞名詞って名詞な名詞な名詞やな",
    "bookmark_count": 0,
    "category": null
  },
  {
    "masuda_id": "20200131175024",
    "title": "anond:20200131174932",
    "content": "お名詞と名詞の名詞名詞はうみべを名詞。",
    "bookmark_count": 0,
    "category": null
  },
  {
    "masuda_id": "20200131175005",
    "title": "anond:20200131162212",
    "content": "名詞だが名詞名詞が名詞.名詞あった名詞までかかっちゃううう名詞、名詞名詞名詞は名詞名詞名詞名詞されない名詞だな名詞としては全然形容詞名詞ねーな名詞",
    "bookmark_count": 0,
    "category": null
  },
  {
    "masuda_id": "20200131175003",
    "title": "",
    "content": "名詞：名詞被っても形容詞ですか？名詞：どうぞ。ところで名詞に名詞名詞くらいお被りに？名詞：名詞くらいですね。名詞：被名詞名詞は名詞くらいですか？名詞：名詞くらいですね。名詞：なるほど。名詞に名詞が停まってますね。名詞：停まってますね。名詞：もし名詞が名詞を被らなければ、名詞くらい買えた名詞ですよ。名詞：名詞。",
    "bookmark_count": 0,
    "category": null
  },
  {
    "masuda_id": "20200131174940",
    "title": "anond:20200131170856",
    "content": "やはり名詞があろうと名詞名詞といわれてる名詞は名詞形容詞名詞だよな。名詞は手放しては名詞な名詞がよくわかる。",
    "bookmark_count": 0,
    "category": null
  },
  {
    "masuda_id": "20200131174932",
    "title": "",
    "content": "本当に名詞名詞名詞してくれて名詞もしてくれてのんびりとした名詞名詞も名詞もうまれかわりあったら形容詞ね",
    "bookmark_count": 0,
    "category": null
  },
  {
    "masuda_id": "20200131174851",
    "title": "anond:20200131174815",
    "content": "形容詞よ",
    "bookmark_count": 0,
    "category": null
  },
  {
    "masuda_id": "20200131174815",
    "title": "",
    "content": "名詞を名詞に話すだけで名詞が汚れるから、名詞でも描いていた名詞名詞なの？",
    "bookmark_count": 0,
    "category": null
  },
  {
    "masuda_id": "20200131174724",
    "title": "不倫したい奴はまず奥さんに不倫させたらいい ",
    "content": "ちゃんと名詞してる名詞も見る名詞それでまったく名詞つかないなら名詞すれば形容詞",
    "bookmark_count": 0,
    "category": null
  },
  {
    "masuda_id": "20200131174608",
    "title": "今年もいろいろなことがあったね ",
    "content": "名詞に逃げ出した名詞の名詞の名詞で名詞を開けて、名詞は名詞が続いたと思ったら名詞で名詞になって、名詞の名詞名詞名詞が名詞されて、すわ名詞か？と騒がれて、名詞名詞に名詞で名詞が名詞されて、名詞から名詞で名詞。あ、名詞名詞も名詞にさよなら名詞。名詞も残す名詞名詞名詞。名詞、名詞に過ごしましょう。名詞は形容詞名詞になると名詞。",
    "bookmark_count": 0,
    "category": null
  },
  {
    "masuda_id": "20200131174537",
    "title": "anond:20200131155150",
    "content": "名詞と名詞する名詞にはまず名詞名詞の名詞を着て行って名詞を防ごう",
    "bookmark_count": 0,
    "category": null
  },
  {
    "masuda_id": "20200131174523",
    "title": "anond:20200131173800",
    "content": "名詞がこういう名詞だ。",
    "bookmark_count": 0,
    "category": null
  },
  {
    "masuda_id": "20200131174509",
    "title": "anond:20200131101628",
    "content": "名詞の名詞を奪う名詞はあるだろ名詞して名詞だからでもその名詞で名詞の名詞を満たしてやる名詞も生じるよねっていう名詞を名詞するから名詞も名詞したいとかその名詞は名詞の名詞の名詞",
    "bookmark_count": 0,
    "category": null
  },
  {
    "masuda_id": "20200131174350",
    "title": "anond:20200131174253",
    "content": "すでに名詞は出ている。",
    "bookmark_count": 0,
    "category": null
  }
]