[
  {
    "masuda_id": "20200122124705",
    "title": "anond:20200122123750",
    "content": "「この車のエアバックはちゃんと作動するんだろうね？」「もちろんです。当社のエアバッグが開かなかったという苦情は今まで一件も寄せられておりません」",
    "bookmark_count": 0,
    "category": null
  },
  {
    "masuda_id": "20200122124659",
    "title": "anond:20200122124506",
    "content": "なんかどこを軸に想定してるのかわからんけど「同程度の方法で返せば問題ない」って点は大多数の見解と一致するだろ",
    "bookmark_count": 0,
    "category": null
  },
  {
    "masuda_id": "20200122124639",
    "title": "anond:20200122124454",
    "content": "エアーマンが倒せないだよ",
    "bookmark_count": 0,
    "category": null
  },
  {
    "masuda_id": "20200122124636",
    "title": "anond:20200122124428",
    "content": "良識的に考えればエアバッグがひらかないほうがいい。理由はもともと事故がかるいから、エアバッグが開かない。そっちのほうがいい。どんだけのじこ・・・ってのを考えなきゃいけないときに俺らに一律のかいはないし尾sんな事故に想定する事を俺が考えてもしょうがないという派閥",
    "bookmark_count": 0,
    "category": null
  },
  {
    "masuda_id": "20200122124525",
    "title": "anond:20200122124430",
    "content": "4個じゃすぐおなかすくやで",
    "bookmark_count": 0,
    "category": null
  },
  {
    "masuda_id": "20200122124512",
    "title": "anond:20200122120312",
    "content": "あなたの責任ですと言われた所で「で？」だろ。立証する義務も責任もない。",
    "bookmark_count": 0,
    "category": null
  },
  {
    "masuda_id": "20200122124506",
    "title": "anond:20200122124242",
    "content": "内定承諾書ってメールで送られてくるんか？　最低でも書留やろ。内定承諾書が電子サインとか無しのメールonlyで遣り取りされてるならその理屈は正しいが。",
    "bookmark_count": 0,
    "category": null
  },
  {
    "masuda_id": "20200122124456",
    "title": "anond:20200122124340",
    "content": "イケヌマって何唐突に意味不明なこと言う君は頭おかしいのかい",
    "bookmark_count": 0,
    "category": null
  },
  {
    "masuda_id": "20200122124445",
    "title": "",
    "content": "正義マインドをうまく刺激するとデマだろうがバズるという教訓",
    "bookmark_count": 0,
    "category": null
  },
  {
    "masuda_id": "20200122124434",
    "title": "やっぱこの手の規制は半島絡みなんだろうね ",
    "content": "非実在児童ポルノ、著作権侵害罪の非親告罪化、インターネット・ブロッキングに続き、青少年のネットゲーム時間規制問題も、韓国の後を追うように出てきました。国際法・国連システムをレトリックに用いた表現規制の動きに対抗するために、我々もいっそうの国際協力を進めていく必要がありますね。— 荻野幸太郎 / OGINO, Kotaro (@ogi_fuji_npo) 2020年1月22日しかしこうしてみるとやはりこの手の規制を押し進めようとしている連中って統一系なのかな？と思ってしまうね。この手の規制は色々な団体の思惑もあって一概には言えないけど、統一系がこの手の規制を率先して進めていたのは特に児童ポルノ関係の件で社説とかまで出していた時点で明らかだしな。そもそもこの手の規制ばかり進めたせいで日本がここまで経済的文化的に衰退したのも事実だしね。しかし陰謀論に過ぎないけど、ストロングゼロの件だって怪しいもんだなと思えてくるのが不思議。",
    "bookmark_count": 0,
    "category": null
  },
  {
    "masuda_id": "20200122124430",
    "title": "anond:20200122124309",
    "content": "それはお気持ちだけで実際食い始めたら4個くらいでじゅうぶんだろ",
    "bookmark_count": 0,
    "category": null
  },
  {
    "masuda_id": "20200122124428",
    "title": "anond:20200122123357",
    "content": "デブにめし食わせるのと、やせにダイエットさせるのどっちがきつい？",
    "bookmark_count": 0,
    "category": null
  },
  {
    "masuda_id": "20200122124418",
    "title": "anond:20200122123422",
    "content": "ヒザヒザヒザヒザヒザヒザヒザヒザヒザヒザヒザヒジヒジヒジヒジヒジヒジヒジヒジヒジヒザヒジヒザヒジ、・・・痛ェ",
    "bookmark_count": 0,
    "category": null
  },
  {
    "masuda_id": "20200122124356",
    "title": "anond:20200122123435",
    "content": "山本太郎とチンピラ立花を同列に見ちゃうんだ。ふーん自民党でいい、と欠片でも思えるネトウヨの脳みそどうなってんだろ",
    "bookmark_count": 0,
    "category": null
  },
  {
    "masuda_id": "20200122124340",
    "title": "anond:20200122124013",
    "content": "18時までなら好きなだけ食べても太らないとか言ってるやつは池沼",
    "bookmark_count": 0,
    "category": null
  },
  {
    "masuda_id": "20200122124309",
    "title": "",
    "content": "お腹すいたやでビッグマック15個くらい食べたいンゴ",
    "bookmark_count": 0,
    "category": null
  },
  {
    "masuda_id": "20200122124242",
    "title": "anond:20200122115049",
    "content": "問題が重要だろうが軽かろうが企業側もメール一本で済ませてるんだからそのルールに則ってるだけだろう。",
    "bookmark_count": 0,
    "category": null
  },
  {
    "masuda_id": "20200122124209",
    "title": "anond:20200122115532",
    "content": "学生時代は3発くらいは軽く抜けたが",
    "bookmark_count": 0,
    "category": null
  },
  {
    "masuda_id": "20200122124204",
    "title": "anond:20200122123425",
    "content": "局：・・・と、ゆー設定でドラマの脚本おながいしますわ虚淵玄：",
    "bookmark_count": 0,
    "category": null
  },
  {
    "masuda_id": "20200122124149",
    "title": "anond:20200122124049",
    "content": "あの企業の包丁は偶然良く遂げているから機械学習でその偶然を必然にかえよう",
    "bookmark_count": 0,
    "category": null
  },
  {
    "masuda_id": "20200122124136",
    "title": "anond:20200122124013",
    "content": "ワイは体重100kgなんやが、米は一日に5合は食べたいやで",
    "bookmark_count": 0,
    "category": null
  },
  {
    "masuda_id": "20200122124049",
    "title": "anond:20200122123821",
    "content": "包丁はといでも、ほぼ厚みは変わらない。",
    "bookmark_count": 0,
    "category": null
  },
  {
    "masuda_id": "20200122124047",
    "title": "anond:20200122123558",
    "content": "華々しくデビューしたらもう一回ぐらいチャンスあるだろ細々とデビューして誰にも知られぬまま消えていくんや",
    "bookmark_count": 0,
    "category": null
  },
  {
    "masuda_id": "20200122123921",
    "title": "anond:20200122122450",
    "content": "言い…訳？ま、まあ言葉の定義は人それぞれだよなお互いがんばろうな",
    "bookmark_count": 0,
    "category": null
  },
  {
    "masuda_id": "20200122123858",
    "title": "anond:20200122123518",
    "content": "関西弁の定義をせえよ",
    "bookmark_count": 0,
    "category": null
  }
]