[
  {
    "masuda_id": "20200308125527",
    "title": "anond:20200308124430",
    "content": "まぁ、電気炊飯器のなぞなんやろうな２時間コースとかあるからなメニューに",
    "bookmark_count": 0,
    "category": null
  },
  {
    "masuda_id": "20200308125454",
    "title": "anond:20200308125351",
    "content": "そんな夢みたいなことできるわけないだろう！🍣",
    "bookmark_count": 0,
    "category": null
  },
  {
    "masuda_id": "20200308125444",
    "title": "anond:20200308125201",
    "content": "次回から備えられるようになろう憤りを感じるなら有事は販売制限を掛けられてるよう意見を募れ",
    "bookmark_count": 0,
    "category": null
  },
  {
    "masuda_id": "20200308125402",
    "title": "毒親さぁ ",
    "content": "いつもキレててきしょいし話しかけると全てにキレて返されるからキッッッモ",
    "bookmark_count": 0,
    "category": null
  },
  {
    "masuda_id": "20200308125351",
    "title": "anond:20200308124250",
    "content": "ギャルと濃厚接触？",
    "bookmark_count": 0,
    "category": null
  },
  {
    "masuda_id": "20200308125317",
    "title": "anond:20200308124211",
    "content": "俺は今ギャルの相手してて忙しいから",
    "bookmark_count": 0,
    "category": null
  },
  {
    "masuda_id": "20200308125307",
    "title": "anond:20200308125159",
    "content": "オラッ（金的）",
    "bookmark_count": 0,
    "category": null
  },
  {
    "masuda_id": "20200308125201",
    "title": "",
    "content": "「『デマ』というのはですね、嘘吐きの言葉なんです。供給を止めてしまわないからデマになるんですよ」 「？」 「供給を止めてしまわないからデマになるんです。供給を止めてしまえばデマじゃ無くなります」 「いやいやいや、順序としては『デマに踊らされる→供給が追いつかなくなってしまう』んですよね？」 「いえ、供給してしまうからデマになるんです」 「？」 「売るんです。買い占めされようがが転売されようが、とにかく売り切れるまで全力で売らせる」 「売り切れるまで」 「そうすればもうデマとは口が裂けても言えないでしょう」 「…んん？？」 「デマじゃなかったって事です。実際に売り切れたのだから。『デマ』という言葉は嘘だった」 「いや、売り切れたんじゃなく売り切れさせたって事でしょ。買い占めされても転売されても」 「しかし現実として売り切れたのですからデマじゃなかった。その後はもう『デマ』なんて言葉は言わせません」 「それこそ僕には無理だなあ」",
    "bookmark_count": 0,
    "category": null
  },
  {
    "masuda_id": "20200308125159",
    "title": "anond:20200308124514",
    "content": "いちいち書き込んでるんじゃねえよ",
    "bookmark_count": 0,
    "category": null
  },
  {
    "masuda_id": "20200308125153",
    "title": "anond:20200308124430",
    "content": "外国人よりも先に、京都以外の日本人が知らないんだよ。そんなに知られた話じゃないんでは。ぶぶづけは。京都は修学旅行でしか行ったこと無いから、自分も詳しい条件もわからない。おかわりが悪いのか、ぶぶづけの単語が出て来たら、帰れの意味なのか。",
    "bookmark_count": 0,
    "category": null
  },
  {
    "masuda_id": "20200308125032",
    "title": "",
    "content": "もう３度目の結婚は断やけどごめんなさいいわずにすなおにてめーがわるいでええんやで",
    "bookmark_count": 0,
    "category": null
  },
  {
    "masuda_id": "20200308124934",
    "title": "anond:20200308124534",
    "content": "何年前からやっててどんだけノウハウたまったの？けっこういろいろなシステムあるけどなんやろうなその問題点＝ノウハウを競合他社におしえるわけにもいかんしどこがけつもちしてかついどるかやろうな",
    "bookmark_count": 0,
    "category": null
  },
  {
    "masuda_id": "20200308124913",
    "title": "",
    "content": "甲子炎",
    "bookmark_count": 0,
    "category": null
  },
  {
    "masuda_id": "20200308124733",
    "title": "anond:20200308124430",
    "content": "待ってても出てこないなら都市伝説的な嫌味として成立するけど出てきてますやんお茶漬けおいしい",
    "bookmark_count": 0,
    "category": null
  },
  {
    "masuda_id": "20200308124534",
    "title": "",
    "content": "リモートワークという単語が気になってしょうがない。東京都はテレワークと言ってるのでいいんだが、総務省がリモートワークという単語を今回の件で使ったりしてるおかげで、割とリモートワークという言葉の方が多く使われている気がする。遠隔地で働くのはどちらも同じだが、リモートワークは、あくまで労働者が社内のネットワークへ入って作業する方法で、これってリスクや金額の面で中小企業には壁が高い。対してテレワークという言葉であれば、リモートワークの形態も含まれるけれど、例えば、メールや電話で連絡するとか、ストレージサービス使ってファイルの受け渡しするとか、割と個人レベルでやってる事の延長線上だから、みんなが使いやすい形態。テレワークという言葉で統一すべきだと思う。でも、相変わらずメディアがリモートワークを使うので、リモートワーク優勢なんだよな。",
    "bookmark_count": 0,
    "category": null
  },
  {
    "masuda_id": "20200308124532",
    "title": "anond:20200308124430",
    "content": "ディレクターの指示やで",
    "bookmark_count": 0,
    "category": null
  },
  {
    "masuda_id": "20200308124514",
    "title": "",
    "content": "タマキックマスター",
    "bookmark_count": 0,
    "category": null
  },
  {
    "masuda_id": "20200308124430",
    "title": "テレ東の京都特集で ",
    "content": "日本文化を学びに来た外国人が、京都の古民家でぶぶ漬けをお代わりしてた。文化を学べたのだろうか？",
    "bookmark_count": 0,
    "category": null
  },
  {
    "masuda_id": "20200308124325",
    "title": "anond:20200308123725",
    "content": "じゃあ食べようぜ！！🍣",
    "bookmark_count": 0,
    "category": null
  },
  {
    "masuda_id": "20200308124250",
    "title": "anond:20200308124109",
    "content": "行こうぜ！！俺は今から駅前に行く！！🍣",
    "bookmark_count": 0,
    "category": null
  },
  {
    "masuda_id": "20200308124218",
    "title": "",
    "content": "おっぱい",
    "bookmark_count": 0,
    "category": null
  },
  {
    "masuda_id": "20200308124211",
    "title": "anond:20200308124133",
    "content": "は？なんなのおまえ俺じゃなくて作者をつぶしに行けよ二度と増田にこれないようにしてやれ",
    "bookmark_count": 0,
    "category": null
  },
  {
    "masuda_id": "20200308124133",
    "title": "anond:20200308124048",
    "content": "サイコロキッズは？",
    "bookmark_count": 0,
    "category": null
  },
  {
    "masuda_id": "20200308124114",
    "title": "anond:20200308124019",
    "content": "察してやれ",
    "bookmark_count": 0,
    "category": null
  },
  {
    "masuda_id": "20200308124109",
    "title": "anond:20200308123612",
    "content": "俺も行きたい",
    "bookmark_count": 0,
    "category": null
  }
]