[
  {
    "masuda_id": "20200302151506",
    "title": "anond:20200302151351",
    "content": "教育実習という「このままだとお前将来生徒からこういう扱い受けんだぞ」を分からされる制度、卒論発表より酷い。",
    "bookmark_count": 0,
    "category": null
  },
  {
    "masuda_id": "20200302151436",
    "title": "anond:20200302120931",
    "content": "バカを叩いてマウント取る",
    "bookmark_count": 0,
    "category": null
  },
  {
    "masuda_id": "20200302151435",
    "title": "anond:20200302150331",
    "content": "むしろその生成アルゴリズムのプログラムいくらだよ",
    "bookmark_count": 0,
    "category": null
  },
  {
    "masuda_id": "20200302151428",
    "title": "anond:20200302151352",
    "content": "おまえにおもねるために政治やってんじゃないんだが",
    "bookmark_count": 0,
    "category": null
  },
  {
    "masuda_id": "20200302151352",
    "title": "野党の質問が全く不安を払拭する方向じゃないの ",
    "content": "正直見ててつらいです選挙に行くのやめたい",
    "bookmark_count": 0,
    "category": null
  },
  {
    "masuda_id": "20200302151351",
    "title": "教育実習に行った時は女生徒から一切口をきいてもらえなかったな ",
    "content": "共学だから男子もいたけど、クラスの半分から存在しない物体として扱われるのは中々キツイものがありますね",
    "bookmark_count": 0,
    "category": null
  },
  {
    "masuda_id": "20200302151348",
    "title": "anond:20200302151233",
    "content": "書いてあるとおり、いい太鼓とはソートじゃないがぼかして抽象的に言うにはソートが言いやすいからなというノウハウと１００万件とか５千万件とかソートすると個性が出るからおもしろいじゃん",
    "bookmark_count": 0,
    "category": null
  },
  {
    "masuda_id": "20200302151341",
    "title": "anond:20200302080802",
    "content": "よくある規模の 延べ面積 3,000m2（約1000人収容）のビルに対し、駐輪場は20台あればいいほう。50人に一人が自転車で通勤しただけでパンクするのが都会の交通事情。原付ほか自動二輪はもっと少ない（ゼロが基本、あっても1000人に1台分ぐらいかな？）まあ路駐しても反則切符切られない路地裏みたいなところでちょくちょくやってる人はいないでもないが数千人に一人ぐらいかな？また業務上交通費が電車か徒歩でないと出ない会社も多い。環境云々や健康云々で意識が進んでいるところで自転車を認めるところもないことはない、というぐらい。",
    "bookmark_count": 0,
    "category": null
  },
  {
    "masuda_id": "20200302151233",
    "title": "anond:20200302150331",
    "content": "逆に語彙が少なすぎてガの字認定してるけどな…なんでソートにそこまで拘ってるんだよ、今は大体どの言語でもSortedListみたいなの実装してるんに…って思うわ。",
    "bookmark_count": 0,
    "category": null
  },
  {
    "masuda_id": "20200302151227",
    "title": "anond:20200302151131",
    "content": "あいてが自分の思ったとおりに動かないのはあいての知能が足りないからだというのは業界なしにしようぜそういうこともあるさおつかれ",
    "bookmark_count": 0,
    "category": null
  },
  {
    "masuda_id": "20200302151142",
    "title": "anond:20200228212452",
    "content": "でも高く売ったんやろ？それ見てた他のやつは、マスク高く売れるんやって思って、儲けるために買い占めしたやろなだからお前のせいでマスクが手に入らなくなったんやで",
    "bookmark_count": 0,
    "category": null
  },
  {
    "masuda_id": "20200302151132",
    "title": "anond:20200302150657",
    "content": "つまり部屋から出ないとなったら客はマジで出ないし、ゾーニングは出来ているし、厚労省の職員は検査を受けずに霞ヶ関に帰ったりしなかった。ゾーニング出来てたから、死者が出たときに、これは我々が対処する前の感染ですねお気の毒ですが……みたいな発表も確信を持ってできて、国民も防疫に詳しいので説明に納得してマスコミ対応国会対策も完璧だ。　書いてた思ったけど絵空事だわこれ。",
    "bookmark_count": 0,
    "category": null
  },
  {
    "masuda_id": "20200302151131",
    "title": "anond:20200302151020",
    "content": "コンピューターのプログラムは宗教論争（この場合は、趣味の問題の意味）って言われる理屈がわかってきた",
    "bookmark_count": 0,
    "category": null
  },
  {
    "masuda_id": "20200302151020",
    "title": "anond:20200302150949",
    "content": "相手がバカだからとか知らないからではなくそうなった理屈を言ってみ？",
    "bookmark_count": 0,
    "category": null
  },
  {
    "masuda_id": "20200302150949",
    "title": "anond:20200302150315",
    "content": "逆になんでそううったかわかる？",
    "bookmark_count": 0,
    "category": null
  },
  {
    "masuda_id": "20200302150939",
    "title": "anond:20200302150609",
    "content": "それは「足し算のおいしさは？」と聞かれてるようなもんなんやでって言って理解できるか理解できないかやな。そも、クイックソートすると計算量如何よりもメモリをどれだけ食うようになるのか、を分かっているのならばプラグマティズム的にそういう話題に達しないってわかると思うんだが。",
    "bookmark_count": 0,
    "category": null
  },
  {
    "masuda_id": "20200302150852",
    "title": "anond:20200302150740",
    "content": "ふるさと納税をモラルの問題にするやつは逝ってよし",
    "bookmark_count": 0,
    "category": null
  },
  {
    "masuda_id": "20200302150802",
    "title": "anond:20200302150609",
    "content": "バイナリーソートとクイックソートを比べてバイナリーソートのほうが良い場合は？",
    "bookmark_count": 0,
    "category": null
  },
  {
    "masuda_id": "20200302150757",
    "title": "anond:20200302150703",
    "content": "「からの～？」で解決",
    "bookmark_count": 0,
    "category": null
  },
  {
    "masuda_id": "20200302150741",
    "title": "",
    "content": "地下鉄で換気運転したら隧道内がウイルスまみれにならない？",
    "bookmark_count": 0,
    "category": null
  },
  {
    "masuda_id": "20200302150740",
    "title": "anond:20200302120931",
    "content": "ふるさと納税はモラルが！とかいって反対しつつデマで品薄になるのは事実だから(買い占めする)って人、一定数いそうで怖い",
    "bookmark_count": 0,
    "category": null
  },
  {
    "masuda_id": "20200302150703",
    "title": "最後の一葉で最後の一葉が意外と下手だったらどうすんの ",
    "content": "娘さんも「葉っぱのつもりで描いてるんだろうし葉っぱに見えた事にしよう」と気を使ってしまうの？",
    "bookmark_count": 5,
    "category": null
  },
  {
    "masuda_id": "20200302150657",
    "title": "anond:20200302150537",
    "content": "もちろん、防疫一般の知識はあることにしていいよ。降ろさない、且つ集団感染させないために、防疫一般の知識があると、どういう対応になるの？",
    "bookmark_count": 0,
    "category": null
  },
  {
    "masuda_id": "20200302150626",
    "title": "anond:20200302120632",
    "content": "本場のイギリス人のBBQに対する情熱はすごいものがあるらしいんやけど、連中はアレを自分たちで料理だと思ってないんかな。下味付けとか焼き加減とかいろいろうるさくて、手間のかかり具合は料理だと言っていいと思うのだけど。焼肉もそういうもんなんでは。たぶん。",
    "bookmark_count": 0,
    "category": null
  },
  {
    "masuda_id": "20200302150609",
    "title": "anond:20200302150514",
    "content": "じゃぁ、クイックソートの難しさは？",
    "bookmark_count": 0,
    "category": null
  }
]