[
  {
    "masuda_id": "20200309170352",
    "title": "anond:20200309170059",
    "content": "頭は悪いけど良い奴っていうのはフィクションにはよくある人物造型だけど、実在しないと俺は思ってるんだ",
    "bookmark_count": 0,
    "category": null
  },
  {
    "masuda_id": "20200309170315",
    "title": "ドザえもんの映画",
    "content": "結構名作ばっかだよね",
    "bookmark_count": 88,
    "category": null
  },
  {
    "masuda_id": "20200309170240",
    "title": "",
    "content": "都心近くで、結構な咳をしているのにも関わらず、電車に乗っている女性が居たんだけど、このご時世に咳がでるのに電車にのるって、公衆衛生観念ないのかな。",
    "bookmark_count": 0,
    "category": null
  },
  {
    "masuda_id": "20200309170233",
    "title": "anond:20200309165643",
    "content": "趣味はレーション携帯での、サバイバルシュミレーションと覚えよう",
    "bookmark_count": 0,
    "category": null
  },
  {
    "masuda_id": "20200309170117",
    "title": "anond:20200309165533",
    "content": "やっぱそれなんだよね。少しも心に響かない作品に感想書こうという気にならないもんな",
    "bookmark_count": 0,
    "category": null
  },
  {
    "masuda_id": "20200309170059",
    "title": "anond:20200309170038",
    "content": "意外といいやつだよ",
    "bookmark_count": 0,
    "category": null
  },
  {
    "masuda_id": "20200309170054",
    "title": "「感染者が出たら休校」→妥当 「全校休校」→やりすぎ ←なんで？ ",
    "content": "感染しているかどうかは分かりません。症状出ていなくてもうつります。としたとき、「学校の方が安全」なら・・・→「感染した」と分かってもその人だけ隔離した方が安全。「学校の方が危険」なら・・・→全校休校にした方が安全。ジョーカー持ちが分からないから。どっちかしかないよね。「全校休校要請とかアホだけど感染者が出たら休校は妥当」の意味が分からんが。だって感染者分からんのよ？めっちゃ潜伏するし検査も全員は無理って散々言われてるよね。出てきそうな言い訳は、身近ででると子供の危機意識高まって相対的に学校の方が危険になる→もしこれ最初から言ってましたよ～って言うならもはやどっかの総理大臣レベルのねつ造言説。もともと全校休校のタイミングの問題視か議論してない→どっかの総理大臣レベルの嘘つきやな。都合の悪いことは歴史改変。医師会の見解でも「地域の状況に応じて学校の臨時休校」って言ってたし→感染者出てない地域ってどこよ。「ここ2週間」の正念場ではそんな後手対応はおかしいでしょ。『温度感』を巧妙に変化させて叩きたいものを叩くって、すげー卑怯じゃん。別に政権なんてどうでもいいけど、そういうのが嫌いなんだよ俺は。",
    "bookmark_count": 0,
    "category": null
  },
  {
    "masuda_id": "20200309170038",
    "title": "anond:20200309165918",
    "content": "増田とも距離とれよ",
    "bookmark_count": 0,
    "category": null
  },
  {
    "masuda_id": "20200309170007",
    "title": "anond:20200309131217",
    "content": "お前がそう思うなら、そうなんだろう。お前の中ではな。",
    "bookmark_count": 0,
    "category": null
  },
  {
    "masuda_id": "20200309165940",
    "title": "anond:20200309165831",
    "content": "いやそういうこと言ってるんじゃなくて。まあいいやマジで言ってたんならほっときゃよかった",
    "bookmark_count": 0,
    "category": null
  },
  {
    "masuda_id": "20200309165918",
    "title": "anond:20191030222257",
    "content": "ありがとう。久々にまた鬱になったから見てみたらまさかこんな真剣な返答もらえてるとは思ってもみなかった。なんかそれだけで気分軽くなった。気質はしょうがねえな。ツイッターと距離とってみる。",
    "bookmark_count": 0,
    "category": null
  },
  {
    "masuda_id": "20200309165916",
    "title": "こういうときだからこそ、大きめの買い物をするぞ！！ ",
    "content": "と思って、土日に出かけようと思ったんだけれども喉が痛くて、鼻水がでて、目が乾き、脱力感が激しいので、家で寝ることにした。旧型コロナだろうけれど、ホント空気読めよ",
    "bookmark_count": 0,
    "category": null
  },
  {
    "masuda_id": "20200309165913",
    "title": "anond:20200309165746",
    "content": "だよなーペーパーにしても1人1ロットは常においとけよと思う",
    "bookmark_count": 0,
    "category": null
  },
  {
    "masuda_id": "20200309165907",
    "title": "anond:20200309165528",
    "content": "トールキンをポリコレ化したのがジョージ・ルーカスだ。ここテストに出るところだぞ～",
    "bookmark_count": 0,
    "category": null
  },
  {
    "masuda_id": "20200309165831",
    "title": "anond:20200309164907",
    "content": "人は理屈より感情で動くっていま社会実験してるところじゃん",
    "bookmark_count": 0,
    "category": null
  },
  {
    "masuda_id": "20200309165826",
    "title": "anond:20200306143803",
    "content": "むしろみんな平常時から家に余分のパックを置いてないことが驚きだわ",
    "bookmark_count": 0,
    "category": null
  },
  {
    "masuda_id": "20200309165712",
    "title": "anond:20200309165528",
    "content": "面白いからもっといろいろこじつけて",
    "bookmark_count": 0,
    "category": null
  },
  {
    "masuda_id": "20200309165710",
    "title": "anond:20200309165528",
    "content": "1900年代前半から最近なのか",
    "bookmark_count": 0,
    "category": null
  },
  {
    "masuda_id": "20200309165651",
    "title": "",
    "content": "布教のやり方がわからん。というか布教は義務なのだろうか。それなりにいくつか私が好きで好きでたまらないコンテンツはあるが、それは私が運命の時に運命の出会いをしたから好きなのであって、別に他人が私と同じものを好きになるとは思わないし、別に好きになってくれなくてい。人がコンテンツにハマる条件に一番に大切なのはタイミングだと思っている。何かを求めているタイミングで出会ってしまったからハマる。良質であることは必要条件かもしれないが十分条件ではないのだ。だから私はこれが好きですとはひっそりと言うが、別にこちら側へ来なくてもいい。",
    "bookmark_count": 0,
    "category": null
  },
  {
    "masuda_id": "20200309165643",
    "title": "シミュレーションは ",
    "content": "趣味じゃない、と覚えよう",
    "bookmark_count": 0,
    "category": null
  },
  {
    "masuda_id": "20200309165627",
    "title": "anond:20200309165528",
    "content": "考えたことなかった",
    "bookmark_count": 0,
    "category": null
  },
  {
    "masuda_id": "20200309165533",
    "title": "anond:20200309163854",
    "content": "ここにアップしてみれば？あと、読者的には微妙な作品は感想書きにくいっす",
    "bookmark_count": 0,
    "category": null
  },
  {
    "masuda_id": "20200309165528",
    "title": "最近のファンタジー小説は人種差別の温床 ",
    "content": "元ネタがどうあれエルフ→白人ドワーフ→アジア人ゴブリン,オーク→黒人を暗に表してるのは明らか。",
    "bookmark_count": 0,
    "category": null
  },
  {
    "masuda_id": "20200309165455",
    "title": "anond:20200309120848",
    "content": "ラ！の住人では無いけど件の人の絵はフォロワーのＲＴから見かけたことがあってこの投稿読んで「あの人じゃね？」と思ったたらやっぱりその当人だったわ二次創作界隈、全部「二次創作なんだから何しても何作っても自由」みたいなスタンスでいる人多いけど、色紙もグッズも特に疑問も罪悪感もなく売れる人たちの感性、普通に引く",
    "bookmark_count": 0,
    "category": null
  },
  {
    "masuda_id": "20200309165429",
    "title": "anond:20200309000539",
    "content": "みんな同作者の「名探偵に薔薇を」も是非読んでくれ",
    "bookmark_count": 0,
    "category": null
  }
]