[
  {
    "masuda_id": "20200129204501",
    "title": "なは ",
    "content": "なはhttp://regarder-streaming-direct-live-gratuit-diffusiontv.over-blog.com/http://regarder-charleroi-bruges-endirect-streaming-live.over-blog.com/2020/01/regarder-charleroi-bruges-en-direct-streaming-live-diffusion-tv-gratuit.htmlhttp://regarder-charleroi-bruges-endirect-streaming-live.over-blog.com/diffusion-tv-proximus",
    "bookmark_count": 0,
    "category": null
  },
  {
    "masuda_id": "20200129204451",
    "title": "anond:20200129204142",
    "content": "ちんちん！",
    "bookmark_count": 0,
    "category": null
  },
  {
    "masuda_id": "20200129204157",
    "title": "どうして海外製ばかりになったんだろうな ",
    "content": "海外の方が技術力が高くとも国内産業を育てるために関税で国が守るというのは重工業までは普通だった。パソコンのCPUやGPUやらマザボは海外製。スマフォも一時期日本製の部品が使われていると言われてたが割合は減っていっている。それ以外の組み込みチップもArmだったり海外製。ソフトもWindowsやVisualStudioも。アニメや漫画が強いといいつつも、制作にはAdobe他、海外ソフトが必要。出版も海外ソフトが必要。CGや製造関係のソフトも海外が多い。ゲームが強いと言われるが制作に必要なのは海外製だろう。Web関係もほとんどが海外。アメリカが強すぎるのは確かだが、何が悪かったのだろうか。1つ目は規模、2つ目はハードへの投資。Googleの一面はソフトウエア会社だが、差別化を支えているのは大量のサーバーやルーターだ。これからはハードではなくソフトで差別化する時代と新聞などではいうが、ハードが進化しなければソフトでは理論演算能力以上は超えられない。初代iPhoneのハードを使って今のiPhoneXやpixel4を超えるソフトが作れると言われたら、多くの人は疑うのではないだろうか。要は両方必要だった。3つ目は情報収集能力で、ニュースメディアに出る前の段階で、どれだけ情報を仕入れられ分析できるか。フランスのYoleのような技術分析ができる企業は日本にそうそうない。Googleだってネットに載らないようなオフラインカンファレンスでの情報収集には社員を送り込んだりしている。",
    "bookmark_count": 2,
    "category": null
  },
  {
    "masuda_id": "20200129204142",
    "title": "anond:20200129204107",
    "content": "ワシはお手が得意やで",
    "bookmark_count": 0,
    "category": null
  },
  {
    "masuda_id": "20200129204119",
    "title": "anond:20200129203655",
    "content": "運転手は死んでもええんか？！",
    "bookmark_count": 0,
    "category": null
  },
  {
    "masuda_id": "20200129204107",
    "title": "なんか女子の目が積極的で最近",
    "content": "ナンパできそうなんだけど。待ってるの？声かけられたい？",
    "bookmark_count": 0,
    "category": null
  },
  {
    "masuda_id": "20200129203815",
    "title": "",
    "content": "どこまでストレスをためられるか試したいんやろうな。",
    "bookmark_count": 0,
    "category": null
  },
  {
    "masuda_id": "20200129203757",
    "title": "anond:20200129202637",
    "content": "例えばインフルエンザで免疫力が下がったところを、別の細菌が肺を荒らして肺炎になるみたいなことはあるですよ。",
    "bookmark_count": 0,
    "category": null
  },
  {
    "masuda_id": "20200129203730",
    "title": "anond:20200129203655",
    "content": "わてはちがうけど、こういう自粛費用じばらなんやで",
    "bookmark_count": 0,
    "category": null
  },
  {
    "masuda_id": "20200129203655",
    "title": "anond:20200129203505",
    "content": "海外旅行帰りでも、念のためタクシーで移動するなどしてるひとが、あわれやな。",
    "bookmark_count": 0,
    "category": null
  },
  {
    "masuda_id": "20200129203652",
    "title": "俺の性格が悪いのは毒親と毒兄に育てられたせい ",
    "content": "どうにもならん",
    "bookmark_count": 0,
    "category": null
  },
  {
    "masuda_id": "20200129203516",
    "title": "anond:20200129203354",
    "content": "男同士はらをわてはなしたい　男と女なら難しいと思われるが　男同士だと簡単だと思われるからな",
    "bookmark_count": 0,
    "category": null
  },
  {
    "masuda_id": "20200129203505",
    "title": "満員電車でも簡単に座れる方法教えてやる ",
    "content": "武漢から帰ってきたばかりだという、紙を首から下げてるだけで、どんな満員電車も悠々自適ほんまみんな馬鹿やな",
    "bookmark_count": 0,
    "category": null
  },
  {
    "masuda_id": "20200129203446",
    "title": "anond:20200129202854",
    "content": "だから平成日本でYouTubeが生まれなかったのさ。iPodはじめ色々。ちなみに、戦後昭和は逆で、ソニーがアメリカのテレビ局にビデオで訴えられて、勝訴してる。なんか窮屈だよね。YouTubeでは2次創作は、認めたんだっけ？任天堂。なんか子供や外国人の夢を壊す感じ。",
    "bookmark_count": 0,
    "category": null
  },
  {
    "masuda_id": "20200129203416",
    "title": "他人に向けた悪意は自分に跳ね返ってくる ",
    "content": "他人に悪意をぶつけるためには自分が強くならねばならない",
    "bookmark_count": 0,
    "category": null
  },
  {
    "masuda_id": "20200129203411",
    "title": "英才教育に躍起になる親 ",
    "content": "子供に夢を託すな無駄のない素晴らしい人生を送らせようとするなお前の後悔を晴らす道具にするな理想の道を少しでも外れたらそれは失敗作なのか？目の前にいるのは人間だふざけるな",
    "bookmark_count": 0,
    "category": null
  },
  {
    "masuda_id": "20200129203357",
    "title": "anond:20200129201934",
    "content": "バカ",
    "bookmark_count": 0,
    "category": null
  },
  {
    "masuda_id": "20200129203355",
    "title": "ドッキリ！ドッキリ！ドンドン！ ",
    "content": "不思議な力が湧いたらど〜しよ",
    "bookmark_count": 0,
    "category": null
  },
  {
    "masuda_id": "20200129203354",
    "title": "anond:20200129203243",
    "content": "むかしは、女による男へのセクハラが映画になったもんだけど、男による男へのセクハラの時代か。まじめに男性が好きな男性が被害を受けるんだろうな。",
    "bookmark_count": 0,
    "category": null
  },
  {
    "masuda_id": "20200129203348",
    "title": "https://anond.hatelabo.jp/20200128222818",
    "content": "増田は警察署からどうやって帰ったの？",
    "bookmark_count": 0,
    "category": null
  },
  {
    "masuda_id": "20200129203301",
    "title": "anond:20200129203043",
    "content": "ワイの会社(＠saitamasaitama)で住み込みで働いても良いぞう。月3000円位なら給料払うしご飯くらいなら支給するぞーん。",
    "bookmark_count": 0,
    "category": null
  },
  {
    "masuda_id": "20200129203255",
    "title": "anond:20200129202637",
    "content": "ワイは何年か前肺炎になって健康診断のレントゲン検査に引っかかったことあるやで",
    "bookmark_count": 0,
    "category": null
  },
  {
    "masuda_id": "20200129203254",
    "title": "anond:20200129151730",
    "content": "105円以内で一番満足出来るお菓子1 名前：びぷます 投稿日：2007/12/15(土) 16:57:41.75 ID:HPIO0w/rO50円＋50円等の組み合わせでもおｋ俺はウエハース2 名前：以下、名無しにかわりましてVIPがお送りします。 投稿日：2007/12/15(土) 16:58:26.07 ID:jz6X144K0うまい棒*10俺は人間",
    "bookmark_count": 0,
    "category": null
  },
  {
    "masuda_id": "20200129203243",
    "title": "anond:20200129203117",
    "content": "セクハラだろうな、最近は、仁義のある人もいるけど男による男へのセクハラもあるんだろうな。",
    "bookmark_count": 0,
    "category": null
  },
  {
    "masuda_id": "20200129203237",
    "title": "常夜鍋を初めて作った ",
    "content": "なんか失敗した感がある　汁がメッチャキツイ味する敗因:干し椎茸が余ってるからって入れすぎた？ほうれん草の下茹で不足？でもゆずポンにつけて食うとかなりうまい　もしかして元々ポン酢ありきの料理？だったらわざわざ酒で煮たりほうれん草使ったりする必要はないのでは…ムムム……",
    "bookmark_count": 0,
    "category": null
  }
]