[
  {
    "masuda_id": "20200228073131",
    "title": "anond:20200228072644",
    "content": "単に、間違ってゴミ箱に名刺入れが落ちたのでは？",
    "bookmark_count": 0,
    "category": null
  },
  {
    "masuda_id": "20200228072908",
    "title": "anond:20200228072505",
    "content": "それで騒いでるんだと思ってた",
    "bookmark_count": 0,
    "category": null
  },
  {
    "masuda_id": "20200228072856",
    "title": "anond:20200228072127",
    "content": "そのランクだと筋が多いほうがむしろ高いんじゃなかったっけ？",
    "bookmark_count": 0,
    "category": null
  },
  {
    "masuda_id": "20200228072837",
    "title": "コロナ予想だよ ",
    "content": "観戦拡大で封鎖が予想されるのはここだ！:大阪そして、優雅に最後まで封鎖されないのはここだ！:群馬",
    "bookmark_count": 0,
    "category": null
  },
  {
    "masuda_id": "20200228072644",
    "title": "anond:20200228072622",
    "content": "会社の警備このていどだったんだなぁと",
    "bookmark_count": 0,
    "category": null
  },
  {
    "masuda_id": "20200228072622",
    "title": "",
    "content": "会社で名刺入れ盗まれた、もう２度と連絡できない人とかふえてしまった。",
    "bookmark_count": 0,
    "category": null
  },
  {
    "masuda_id": "20200228072505",
    "title": "ウイルス検査を断るのは ",
    "content": "もちろん人数など色々な理由はあるのでしょうけど、自然治癒も一応可能なウイルスですので日本はこれ以上感染者を増やしたくない（数字で）のではと勘ぐってしまいます。オリンピックもありますし。",
    "bookmark_count": 0,
    "category": null
  },
  {
    "masuda_id": "20200228072452",
    "title": "anond:20200228072324",
    "content": "でいくら？ってきけるのもすごいけどなかねなんていらいらないっていわれてラッキー安く済んだとかな人間は本当にすごい",
    "bookmark_count": 0,
    "category": null
  },
  {
    "masuda_id": "20200228072410",
    "title": "anond:20200228071951",
    "content": "声が大きい=複数IDてやつだねばらせばいいのに。tor含めて。",
    "bookmark_count": 0,
    "category": null
  },
  {
    "masuda_id": "20200228072354",
    "title": "anond:20200228072243",
    "content": "受け皿になってるテーマパークとかも全休でいいのにな危険すぎるでしょ",
    "bookmark_count": 0,
    "category": null
  },
  {
    "masuda_id": "20200228072324",
    "title": "anond:20200228072143",
    "content": "一生懸命被害者の閉じた心を開かせようと話しかける加害者たちを見ているとかぞくなら、自分は加害者じゃないと主張しているようですごいなっておもうおわっちゃったこの人生を見るとつらい",
    "bookmark_count": 0,
    "category": null
  },
  {
    "masuda_id": "20200228072243",
    "title": "子供がクラスのLINE見せてくれた ",
    "content": "みんなディズニー行くとか遊びに行く約束してるみたい流石安倍ちゃんや！",
    "bookmark_count": 0,
    "category": null
  },
  {
    "masuda_id": "20200228072150",
    "title": "anond:20200228071954",
    "content": "なんで2回書くねんなんで2回書くねん",
    "bookmark_count": 0,
    "category": null
  },
  {
    "masuda_id": "20200228072143",
    "title": "",
    "content": "４０の女が４６をこえたみたいなはなしにごめんなさいっていえるやつの気が知れないせめて普通に対応してる　ふれないその話には",
    "bookmark_count": 0,
    "category": null
  },
  {
    "masuda_id": "20200228072127",
    "title": "anond:20200228065303",
    "content": "値段の差額いきなりステーキ千円以上しなかったっけ？ちなみに、立ち食いデフォルトだった時期に注文したら、筋がやたら多い肉出してきて千円前後取られたので、それ以来行ってない",
    "bookmark_count": 0,
    "category": null
  },
  {
    "masuda_id": "20200228072055",
    "title": "街が静か ",
    "content": "顧客からの回答も、発注先からの納品もなくて、テレワークで「いつかやろう」と思っていた仕事を黙々と片付けている。それでもなんかのんびりしてしまって、ドアを開けて外に出ればいつもは朝一番から騒がしい街がしんと静まり返っていた。普段はそんな余裕もないのだけれども、がらんとした街中を目的もなく散歩することにする。",
    "bookmark_count": 0,
    "category": null
  },
  {
    "masuda_id": "20200228071954",
    "title": "ひとりごとが増えて困る ",
    "content": "歩いているときとか、普通に話す声量でひとりごと言ってる。精神状態がよくない。病院行ったほうがいいのかな。",
    "bookmark_count": 0,
    "category": null
  },
  {
    "masuda_id": "20200228071952",
    "title": "ひとりごとが増えて困る ",
    "content": "歩いているときとか、普通に話す声量でひとりごと言ってる。精神状態がよくない。病院行ったほうがいいのかな。",
    "bookmark_count": 0,
    "category": null
  },
  {
    "masuda_id": "20200228071951",
    "title": "休校にしてもしなくても ",
    "content": "休校にしなかったらしなかったで文句タラタラ休校にしたらしたで非難ごうごう手のひらクルックルだな「世間」ってまあ、前者は単に声が大きい少数派だとは思ってたんだけどさ。まさか政府がこんな決定に出るとは思わなんだ。大衆（かどうか怪しいものだけど）に迎合しすぎ。",
    "bookmark_count": 0,
    "category": null
  },
  {
    "masuda_id": "20200228071923",
    "title": "",
    "content": "社員を首にするのに理由は要らないからな１ヶ月前に通告すればいいだけ（社員としてもそんなことを通告されてのこっていいことがあるわけでもなし、選ぶ会社を間違えたとなくだけ）",
    "bookmark_count": 0,
    "category": null
  },
  {
    "masuda_id": "20200228071411",
    "title": "今日も朝からおはようございまーす ",
    "content": "コロナちゃん、絶賛拡大ちゅー♥️急にお休みになった人も、平常運転まいにちお休み中のみなさんも、いくら休みだからって、お掃除さぼっちゃだめだよー今ここで増田書いてるあなた、そう私も含めた、そこの増田！やることやってから増田しようね♥️",
    "bookmark_count": 0,
    "category": null
  },
  {
    "masuda_id": "20200228071015",
    "title": "anond:20200228070337",
    "content": "自分で稼げないお前がアホそもそもお前働いてないだろ",
    "bookmark_count": 0,
    "category": null
  },
  {
    "masuda_id": "20200228070925",
    "title": "anond:20200228070402",
    "content": "流石大日本帝国の血を引くやつやな物流は人間魚雷ってかwww",
    "bookmark_count": 0,
    "category": null
  },
  {
    "masuda_id": "20200228070923",
    "title": "anond:20200228065303",
    "content": "😷ワイは両方食ったことないやで",
    "bookmark_count": 0,
    "category": null
  },
  {
    "masuda_id": "20200228070753",
    "title": "anond:20200228070726",
    "content": "じゃあそれも",
    "bookmark_count": 0,
    "category": null
  }
]